LICENSE
README.md
pyproject.toml
requirements.txt
dqm/__init__.py
dqm/main.py
dqm/completeness/__init__.py
dqm/completeness/metric.py
dqm/diversity/__init__.py
dqm/diversity/diversity.py
dqm/diversity/metric.py
dqm/domain_gap/__init__.py
dqm/domain_gap/custom_datasets.py
dqm/domain_gap/metrics.py
dqm/domain_gap/utils.py
dqm/representativeness/__init__.py
dqm/representativeness/metric.py
dqm/representativeness/utils.py
dqm/utils/__init__.py
dqm/utils/twe_logger.py
dqm_ml.egg-info/PKG-INFO
dqm_ml.egg-info/SOURCES.txt
dqm_ml.egg-info/dependency_links.txt
dqm_ml.egg-info/entry_points.txt
dqm_ml.egg-info/requires.txt
dqm_ml.egg-info/top_level.txt