Metadata-Version: 2.4
Name: dqm-ml
Version: 1.1.1
Summary: Python library designed to compute data quality metrics for Machine Learning
Author: IRT SystemX
Author-email: support@irt-systemx.fr
License-Expression: MPL-2.0
Project-URL: Homepage, https://irt-systemx.github.io/dqm-ml
Project-URL: Documentation, https://irt-systemx.github.io/dqm-ml
Project-URL: Repository, https://github.com/IRT-SystemX/dqm-ml
Requires-Python: >=3.10
License-File: LICENSE
Requires-Dist: matplotlib
Requires-Dist: numpy
Requires-Dist: pandas
Requires-Dist: setuptools
Requires-Dist: tqdm
Requires-Dist: torch
Requires-Dist: torchvision
Requires-Dist: scipy
Requires-Dist: scikit-learn
Requires-Dist: POT
Requires-Dist: ipykernel
Requires-Dist: seaborn
Requires-Dist: pyaml
Dynamic: license-file
